cfpack/__init__.py
cfpack/automator.py
cfpack/browser_control.py
cfpack/cfpack.mplstyle
cfpack/constants.py
cfpack/hdfio.py
cfpack/matplotlibrc.py
cfpack/mpi.py
cfpack/tests.py
cfpack-0.5.2.dist-info/licenses/LICENSE
cfpack-0.5.2.dist-info/METADATA
cfpack-0.5.2.dist-info/WHEEL
cfpack-0.5.2.dist-info/top_level.txt
cfpack-0.5.2.dist-info/RECORD
