Metadata-Version: 2.4
Name: cfpack
Version: 0.5.2
Summary: Christoph Federrath (CF) python package (cfpack)
Home-page: https://www.mso.anu.edu.au/~chfeder/codes/cfpack/cfpack.html
Author: Christoph Federrath
Author-email: christoph.federrath@anu.edu.au
License: MIT
Project-URL: Source, https://github.com/chfeder/cfpack
Project-URL: Documentation, https://www.mso.anu.edu.au/~chfeder/codes/cfpack/doc/index.html
Classifier: Programming Language :: Python :: 3
Classifier: License :: OSI Approved :: MIT License
Classifier: Operating System :: OS Independent
Requires-Python: >=3
License-File: LICENSE
Requires-Dist: astropy
Requires-Dist: colorama
Requires-Dist: corner
Requires-Dist: emcee
Requires-Dist: ipdb
Requires-Dist: lmfit
Requires-Dist: matplotlib
Requires-Dist: numpy
Requires-Dist: Pandas
Requires-Dist: scipy
Dynamic: author
Dynamic: author-email
Dynamic: classifier
Dynamic: description
Dynamic: description-content-type
Dynamic: home-page
Dynamic: license
Dynamic: license-file
Dynamic: project-url
Dynamic: requires-dist
Dynamic: requires-python
Dynamic: summary
